{
  "generatedAt": "2026-07-10T17:07:15.630Z",
  "count": 100,
  "tips": [
    {
      "id": 8593,
      "name": "Draught of Hunter's Ale",
      "icon": "https://render.guildwars2.com/file/D10D01490B3696490FD727FF69ECD20D10307277/63099.png",
      "rarity": "Basic",
      "buy": 4,
      "sell": 10,
      "supply": 416211,
      "demand": 399756,
      "unitProfit": 4,
      "marginPct": 100,
      "dailyVolumeEstimate": 399756,
      "score": 560.1796077258189
    },
    {
      "id": 68633,
      "name": "Fried Golden Dumpling",
      "icon": "https://render.guildwars2.com/file/B8C00E1A6218DE474EBB355EA81DAED8F7C2CADD/1341427.png",
      "rarity": "Fine",
      "buy": 5,
      "sell": 12,
      "supply": 718835,
      "demand": 210199,
      "unitProfit": 5,
      "marginPct": 100,
      "dailyVolumeEstimate": 210199,
      "score": 532.2632711692224
    },
    {
      "id": 101213,
      "name": "Rift Essence Coffer",
      "icon": "https://render.guildwars2.com/file/DC53E3DCA0B1030DD897A0AB0F0B606DCD994451/3187524.png",
      "rarity": "Masterwork",
      "buy": 2,
      "sell": 6,
      "supply": 379954,
      "demand": 189097,
      "unitProfit": 2,
      "marginPct": 100,
      "dailyVolumeEstimate": 189097,
      "score": 527.6686935542252
    },
    {
      "id": 43909,
      "name": "Lightning Catcher Skin",
      "icon": "https://render.guildwars2.com/file/0CFBB03794F5D8DE9099267EB6F9E3BD0EDA229A/603282.png",
      "rarity": "Rare",
      "buy": 6,
      "sell": 15,
      "supply": 117810,
      "demand": 150653,
      "unitProfit": 6,
      "marginPct": 100,
      "dailyVolumeEstimate": 117810,
      "score": 507.11858423718706
    },
    {
      "id": 74268,
      "name": "Mini Professor Mew",
      "icon": "https://render.guildwars2.com/file/BAF43C0425BA631B9C49E771F9EB16E32C1E57E1/1203237.png",
      "rarity": "Exotic",
      "buy": 3,
      "sell": 8,
      "supply": 1629479,
      "demand": 53931,
      "unitProfit": 3,
      "marginPct": 100,
      "dailyVolumeEstimate": 53931,
      "score": 473.18465258483025
    },
    {
      "id": 24466,
      "name": "Malachite Pebble",
      "icon": "https://render.guildwars2.com/file/0545ACA4031B6A343418223C9B9D601941C29BE2/220909.png",
      "rarity": "Fine",
      "buy": 21,
      "sell": 50,
      "supply": 96707,
      "demand": 35713,
      "unitProfit": 21,
      "marginPct": 100,
      "dailyVolumeEstimate": 35713,
      "score": 455.2838494288028
    },
    {
      "id": 77686,
      "name": "Lucky Guild Firework",
      "icon": "https://render.guildwars2.com/file/B3004CB4D2E6A2F3E99EB6D1F61243AD9D3FE87F/1341439.png",
      "rarity": "Masterwork",
      "buy": 18,
      "sell": 40,
      "supply": 946344,
      "demand": 111623,
      "unitProfit": 16,
      "marginPct": 88.88888888888889,
      "dailyVolumeEstimate": 111623,
      "score": 448.68956277538865
    },
    {
      "id": 71225,
      "name": "Wool Patch",
      "icon": "https://render.guildwars2.com/file/360D24BA0AED40FF2A5E190DE421470EFCD57112/1201854.png",
      "rarity": "Basic",
      "buy": 37,
      "sell": 83,
      "supply": 66434,
      "demand": 103543,
      "unitProfit": 34,
      "marginPct": 91.8918918918919,
      "dailyVolumeEstimate": 66434,
      "score": 443.1391782096621
    },
    {
      "id": 43952,
      "name": "Desert Rose Skin",
      "icon": "https://render.guildwars2.com/file/A71801FBFCE80840E9A70BCF371F062033FAC59D/607529.png",
      "rarity": "Rare",
      "buy": 11,
      "sell": 23,
      "supply": 208899,
      "demand": 402176,
      "unitProfit": 9,
      "marginPct": 81.81818181818183,
      "dailyVolumeEstimate": 208899,
      "score": 435.2676905438435
    },
    {
      "id": 92196,
      "name": "Soul Cake",
      "icon": "https://render.guildwars2.com/file/48121F74932ECE6D75671E5C3C6641F03A92F903/2212631.png",
      "rarity": "Masterwork",
      "buy": 71,
      "sell": 167,
      "supply": 27685,
      "demand": 19817,
      "unitProfit": 71,
      "marginPct": 100,
      "dailyVolumeEstimate": 19817,
      "score": 429.7059824075058
    },
    {
      "id": 8887,
      "name": "Powerful Potion of Inquest Slaying",
      "icon": "https://render.guildwars2.com/file/72E638C510AC04A068DDBC3C7B3C49D1A860C114/222670.png",
      "rarity": "Fine",
      "buy": 259,
      "sell": 589,
      "supply": 33967,
      "demand": 29609,
      "unitProfit": 242,
      "marginPct": 93.43629343629344,
      "dailyVolumeEstimate": 29609,
      "score": 417.79463111513917
    },
    {
      "id": 12990,
      "name": "Bronze Plated Dowel",
      "icon": "https://render.guildwars2.com/file/1A34B1613F19C19997F40295A37E5AD902BB0F31/63487.png",
      "rarity": "Masterwork",
      "buy": 77,
      "sell": 179,
      "supply": 14853,
      "demand": 34360,
      "unitProfit": 75,
      "marginPct": 97.40259740259741,
      "dailyVolumeEstimate": 14853,
      "score": 406.348385023985
    },
    {
      "id": 8884,
      "name": "Powerful Potion of Destroyer Slaying",
      "icon": "https://render.guildwars2.com/file/BC654CB4AFBB18CF6E77A146A83E46BACEFF56CB/222684.png",
      "rarity": "Fine",
      "buy": 136,
      "sell": 319,
      "supply": 15170,
      "demand": 12312,
      "unitProfit": 135,
      "marginPct": 99.26470588235294,
      "dailyVolumeEstimate": 12312,
      "score": 406.0287674475603
    },
    {
      "id": 12354,
      "name": "Meat Pie",
      "icon": "https://render.guildwars2.com/file/981EA539473DDD77F718180FE0091544B87548F3/63381.png",
      "rarity": "Fine",
      "buy": 510,
      "sell": 1198,
      "supply": 11675,
      "demand": 20784,
      "unitProfit": 508,
      "marginPct": 99.6078431372549,
      "dailyVolumeEstimate": 11675,
      "score": 405.13439134284636
    },
    {
      "id": 24534,
      "name": "Amber Pebble",
      "icon": "https://render.guildwars2.com/file/616CA09A677C9B41FCAE746DCD245F04084955D2/220960.png",
      "rarity": "Fine",
      "buy": 22,
      "sell": 49,
      "supply": 65112,
      "demand": 28022,
      "unitProfit": 20,
      "marginPct": 90.9090909090909,
      "dailyVolumeEstimate": 28022,
      "score": 404.31951152720563
    },
    {
      "id": 8890,
      "name": "Powerful Potion of Grawl Slaying",
      "icon": "https://render.guildwars2.com/file/D8AEFEEE53CE4A3B32EE65E52B910F3BC53EF26B/222668.png",
      "rarity": "Fine",
      "buy": 180,
      "sell": 409,
      "supply": 20989,
      "demand": 18155,
      "unitProfit": 168,
      "marginPct": 93.33333333333333,
      "dailyVolumeEstimate": 18155,
      "score": 397.5085495799424
    },
    {
      "id": 8885,
      "name": "Powerful Potion of Elemental Slaying",
      "icon": "https://render.guildwars2.com/file/37F8EECAE2A478AA626E6AAC73D2A3354FE4A90C/222672.png",
      "rarity": "Fine",
      "buy": 148,
      "sell": 348,
      "supply": 8698,
      "demand": 22078,
      "unitProfit": 148,
      "marginPct": 100,
      "dailyVolumeEstimate": 8698,
      "score": 393.946933084353
    },
    {
      "id": 12289,
      "name": "Lemon Bar",
      "icon": "https://render.guildwars2.com/file/A74CD6C6DB585227BD266920AD1BC936DB0D07D2/339902.png",
      "rarity": "Fine",
      "buy": 109,
      "sell": 243,
      "supply": 23605,
      "demand": 35757,
      "unitProfit": 98,
      "marginPct": 89.90825688073394,
      "dailyVolumeEstimate": 23605,
      "score": 393.17082153508204
    },
    {
      "id": 8882,
      "name": "Powerful Potion of Nightmare Court Slaying",
      "icon": "https://render.guildwars2.com/file/E079346EA36BFBBD752B0A18B1A976962C15EEF5/222666.png",
      "rarity": "Fine",
      "buy": 158,
      "sell": 349,
      "supply": 30237,
      "demand": 27637,
      "unitProfit": 139,
      "marginPct": 87.9746835443038,
      "dailyVolumeEstimate": 27637,
      "score": 390.7401386941025
    },
    {
      "id": 75862,
      "name": "Pouch of White Pigment",
      "icon": "https://render.guildwars2.com/file/E20809A539CF3813A92E6832734053F579673FDE/1200715.png",
      "rarity": "Fine",
      "buy": 59,
      "sell": 125,
      "supply": 439533,
      "demand": 61923,
      "unitProfit": 47,
      "marginPct": 79.66101694915254,
      "dailyVolumeEstimate": 61923,
      "score": 381.72436117370523
    },
    {
      "id": 75448,
      "name": "Alpine Lumber Core",
      "icon": "https://render.guildwars2.com/file/BDEAEB0F2A28614313386FD41E07F1D10E4B5775/455860.png",
      "rarity": "Rare",
      "buy": 65,
      "sell": 148,
      "supply": 20578,
      "demand": 11230,
      "unitProfit": 61,
      "marginPct": 93.84615384615384,
      "dailyVolumeEstimate": 11230,
      "score": 380.1161908645434
    },
    {
      "id": 77653,
      "name": "Recipe: Peppermint Oil",
      "icon": "https://render.guildwars2.com/file/E19734B71C949924A1353106E513DE62729A5313/849374.png",
      "rarity": "Masterwork",
      "buy": 2,
      "sell": 6,
      "supply": 43583,
      "demand": 6315,
      "unitProfit": 2,
      "marginPct": 100,
      "dailyVolumeEstimate": 6315,
      "score": 380.04421213362565
    },
    {
      "id": 9288,
      "name": "Bag of Pilfered Goods",
      "icon": "https://render.guildwars2.com/file/EBC5CEC199D1E51B02756A1C796A65E9D24F04B5/63171.png",
      "rarity": "Basic",
      "buy": 257,
      "sell": 595,
      "supply": 8431,
      "demand": 10775,
      "unitProfit": 248,
      "marginPct": 96.49805447470817,
      "dailyVolumeEstimate": 8431,
      "score": 378.84466469703534
    },
    {
      "id": 19704,
      "name": "Lump of Tin",
      "icon": "https://render.guildwars2.com/file/B2705275944046734E4079651E6BB0CC0EEB3943/65932.png",
      "rarity": "Basic",
      "buy": 6,
      "sell": 13,
      "supply": 350157,
      "demand": 34726,
      "unitProfit": 5,
      "marginPct": 83.33333333333334,
      "dailyVolumeEstimate": 34726,
      "score": 378.3889389208702
    },
    {
      "id": 68439,
      "name": "Minor Sigil of Mischief",
      "icon": "https://render.guildwars2.com/file/B43EFAD8ED47F27BC22343935F4F01F167240832/924728.png",
      "rarity": "Masterwork",
      "buy": 127,
      "sell": 280,
      "supply": 22021,
      "demand": 21001,
      "unitProfit": 111,
      "marginPct": 87.4015748031496,
      "dailyVolumeEstimate": 21001,
      "score": 377.7723878818495
    },
    {
      "id": 9302,
      "name": "Tiny Stolen Supplies Bag",
      "icon": "https://render.guildwars2.com/file/EBC5CEC199D1E51B02756A1C796A65E9D24F04B5/63171.png",
      "rarity": "Basic",
      "buy": 65,
      "sell": 150,
      "supply": 13588,
      "demand": 8752,
      "unitProfit": 62,
      "marginPct": 95.38461538461539,
      "dailyVolumeEstimate": 8752,
      "score": 376.0211224076684
    },
    {
      "id": 24303,
      "name": "Charged Shard",
      "icon": "https://render.guildwars2.com/file/306AB62DEBCD6D02113CD0730BDC6F95BA9B9AC4/65587.png",
      "rarity": "Rare",
      "buy": 109,
      "sell": 228,
      "supply": 97033,
      "demand": 66021,
      "unitProfit": 85,
      "marginPct": 77.98165137614679,
      "dailyVolumeEstimate": 66021,
      "score": 375.8472820926605
    },
    {
      "id": 8855,
      "name": "Strong Potion of Elemental Slaying",
      "icon": "https://render.guildwars2.com/file/B1659FED114515F0694A05FB1609B0790FA96DF8/222780.png",
      "rarity": "Fine",
      "buy": 91,
      "sell": 211,
      "supply": 48443,
      "demand": 7491,
      "unitProfit": 88,
      "marginPct": 96.7032967032967,
      "dailyVolumeEstimate": 7491,
      "score": 374.6863776328369
    },
    {
      "id": 12808,
      "name": "Mithril Hook",
      "icon": "https://render.guildwars2.com/file/150169E128399268B770AF420607F0B65AB8A0F3/219495.png",
      "rarity": "Basic",
      "buy": 107,
      "sell": 241,
      "supply": 211115,
      "demand": 12020,
      "unitProfit": 98,
      "marginPct": 91.58878504672897,
      "dailyVolumeEstimate": 12020,
      "score": 373.67680235601074
    },
    {
      "id": 24641,
      "name": "Major Sigil of Undead Slaying",
      "icon": "https://render.guildwars2.com/file/4F4B5EB9F60BE6A31E5DE7120F61E9E5571BD454/340595.png",
      "rarity": "Rare",
      "buy": 148,
      "sell": 344,
      "supply": 7126,
      "demand": 6340,
      "unitProfit": 145,
      "marginPct": 97.97297297297297,
      "dailyVolumeEstimate": 6340,
      "score": 372.5086987919658
    },
    {
      "id": 24663,
      "name": "Minor Sigil of Elemental Slaying",
      "icon": "https://render.guildwars2.com/file/33654F742B6BC79709BDBE5605DCD3F2A6375E5E/221045.png",
      "rarity": "Masterwork",
      "buy": 86,
      "sell": 198,
      "supply": 7997,
      "demand": 12408,
      "unitProfit": 82,
      "marginPct": 95.34883720930233,
      "dailyVolumeEstimate": 7997,
      "score": 372.14473812022703
    },
    {
      "id": 12418,
      "name": "Peach Cookie",
      "icon": "https://render.guildwars2.com/file/58AD6124F72666F1F7390136F4175E6F02377F4B/433612.png",
      "rarity": "Fine",
      "buy": 116,
      "sell": 269,
      "supply": 6222,
      "demand": 26967,
      "unitProfit": 113,
      "marginPct": 97.41379310344827,
      "dailyVolumeEstimate": 6222,
      "score": 369.58791164762516
    },
    {
      "id": 12523,
      "name": "Bowl of Orange Coconut Frosting",
      "icon": "https://render.guildwars2.com/file/170F2704F53FC2785D1EBC67605B145A0D0ACAD7/339962.png",
      "rarity": "Basic",
      "buy": 55,
      "sell": 124,
      "supply": 19154,
      "demand": 9199,
      "unitProfit": 51,
      "marginPct": 92.72727272727272,
      "dailyVolumeEstimate": 9199,
      "score": 367.5512348993151
    },
    {
      "id": 67379,
      "name": "Bottle of Batwing Brew",
      "icon": "https://render.guildwars2.com/file/C4DBF3E24B3C9A1D2CABC55BF500F36C74F81E97/888368.png",
      "rarity": "Rare",
      "buy": 163,
      "sell": 355,
      "supply": 26093,
      "demand": 21747,
      "unitProfit": 138,
      "marginPct": 84.66257668711657,
      "dailyVolumeEstimate": 21747,
      "score": 367.21709617024226
    },
    {
      "id": 19840,
      "name": "Rampager's Hard Inscription",
      "icon": "https://render.guildwars2.com/file/B41A05563ECE6C0A4299089949B30567EE0864EE/66024.png",
      "rarity": "Fine",
      "buy": 531,
      "sell": 1219,
      "supply": 6819,
      "demand": 8036,
      "unitProfit": 505,
      "marginPct": 95.10357815442562,
      "dailyVolumeEstimate": 6819,
      "score": 364.60661190235817
    },
    {
      "id": 12519,
      "name": "Pile of Pumpkin Pie Spice",
      "icon": "https://render.guildwars2.com/file/FF98B1BF45D9CB955B0500AFE9797F9C49D7A6D5/219404.png",
      "rarity": "Basic",
      "buy": 519,
      "sell": 1144,
      "supply": 31490,
      "demand": 14118,
      "unitProfit": 454,
      "marginPct": 87.47591522157995,
      "dailyVolumeEstimate": 14118,
      "score": 363.0078974865256
    },
    {
      "id": 8579,
      "name": "Stein of Hunter's Ale",
      "icon": "https://render.guildwars2.com/file/5B6A00A7056C0DC8DA7448C0B1FC07560C6AD5B7/63092.png",
      "rarity": "Basic",
      "buy": 8,
      "sell": 19,
      "supply": 93836,
      "demand": 4127,
      "unitProfit": 8,
      "marginPct": 100,
      "dailyVolumeEstimate": 4127,
      "score": 361.5739688619155
    },
    {
      "id": 12386,
      "name": "Bowl of Blackberry Pear Compote",
      "icon": "https://render.guildwars2.com/file/C4ABFE75D5463C22030EF97012D89D5E94D1DAF8/339932.png",
      "rarity": "Fine",
      "buy": 93,
      "sell": 202,
      "supply": 27873,
      "demand": 17366,
      "unitProfit": 79,
      "marginPct": 84.94623655913979,
      "dailyVolumeEstimate": 17366,
      "score": 360.1486661705708
    },
    {
      "id": 13257,
      "name": "Green Scepter Core",
      "icon": "https://render.guildwars2.com/file/4F6047AD3CCFD994D569C073CA98CF751206F8AD/219688.png",
      "rarity": "Basic",
      "buy": 21,
      "sell": 49,
      "supply": 4045,
      "demand": 3990,
      "unitProfit": 21,
      "marginPct": 100,
      "dailyVolumeEstimate": 3990,
      "score": 360.1081727784023
    },
    {
      "id": 24470,
      "name": "Lapis Nugget",
      "icon": "https://render.guildwars2.com/file/98345E1004EBC610B76092D27DFFC673F539BD4F/220913.png",
      "rarity": "Fine",
      "buy": 37,
      "sell": 80,
      "supply": 44147,
      "demand": 19550,
      "unitProfit": 31,
      "marginPct": 83.78378378378379,
      "dailyVolumeEstimate": 19550,
      "score": 359.5303736410085
    },
    {
      "id": 8841,
      "name": "Potion of Demon Slaying",
      "icon": "https://render.guildwars2.com/file/6D41597AEC924EE557A8E0D0AFF655D04CEB0D14/222696.png",
      "rarity": "Fine",
      "buy": 543,
      "sell": 1235,
      "supply": 17908,
      "demand": 7105,
      "unitProfit": 506,
      "marginPct": 93.18600368324125,
      "dailyVolumeEstimate": 7105,
      "score": 358.9175603675091
    },
    {
      "id": 75993,
      "name": "Recipe: Viper's Draconic Gauntlets",
      "icon": "https://render.guildwars2.com/file/2165062CDCFBAAA0173AB39DF7EB10A2120816D0/849293.png",
      "rarity": "Exotic",
      "buy": 10,
      "sell": 23,
      "supply": 8753,
      "demand": 3859,
      "unitProfit": 10,
      "marginPct": 100,
      "dailyVolumeEstimate": 3859,
      "score": 358.65873046717553
    },
    {
      "id": 9332,
      "name": "Bag of Theoretical Materials",
      "icon": "https://render.guildwars2.com/file/EBC5CEC199D1E51B02756A1C796A65E9D24F04B5/63171.png",
      "rarity": "Basic",
      "buy": 121,
      "sell": 277,
      "supply": 6154,
      "demand": 6310,
      "unitProfit": 114,
      "marginPct": 94.21487603305785,
      "dailyVolumeEstimate": 6154,
      "score": 357.0016516764266
    },
    {
      "id": 24646,
      "name": "Minor Sigil of Grawl Slaying",
      "icon": "https://render.guildwars2.com/file/6606631F65BD7D99F8B7A0BE2C4B589C0B041720/221028.png",
      "rarity": "Masterwork",
      "buy": 123,
      "sell": 271,
      "supply": 28330,
      "demand": 12097,
      "unitProfit": 107,
      "marginPct": 86.99186991869918,
      "dailyVolumeEstimate": 12097,
      "score": 355.16288868157113
    },
    {
      "id": 9348,
      "name": "Large Bag of Booty",
      "icon": "https://render.guildwars2.com/file/EBC5CEC199D1E51B02756A1C796A65E9D24F04B5/63171.png",
      "rarity": "Basic",
      "buy": 190,
      "sell": 427,
      "supply": 7892,
      "demand": 13304,
      "unitProfit": 173,
      "marginPct": 91.05263157894737,
      "dailyVolumeEstimate": 7892,
      "score": 354.85414936069907
    },
    {
      "id": 24535,
      "name": "Topaz Nugget",
      "icon": "https://render.guildwars2.com/file/11B59BBE4A46F32A33542333B128E81545D93418/220961.png",
      "rarity": "Fine",
      "buy": 41,
      "sell": 87,
      "supply": 44935,
      "demand": 25177,
      "unitProfit": 33,
      "marginPct": 80.48780487804879,
      "dailyVolumeEstimate": 25177,
      "score": 354.2285379606975
    },
    {
      "id": 8866,
      "name": "Potent Potion of Outlaw Slaying",
      "icon": "https://render.guildwars2.com/file/9E69734C5E0EB2E0B7BB36B3B4F6444BB5BF61D6/222646.png",
      "rarity": "Fine",
      "buy": 114,
      "sell": 245,
      "supply": 19656,
      "demand": 23104,
      "unitProfit": 94,
      "marginPct": 82.45614035087719,
      "dailyVolumeEstimate": 19656,
      "score": 354.0268599477226
    },
    {
      "id": 35735,
      "name": "Mystic Frame",
      "icon": "https://render.guildwars2.com/file/6CB10641C2B7FB0568D5239633CD5AAC9CE194E3/486256.png",
      "rarity": "Rare",
      "buy": 6,
      "sell": 14,
      "supply": 3454,
      "demand": 4694,
      "unitProfit": 6,
      "marginPct": 100,
      "dailyVolumeEstimate": 3454,
      "score": 353.84480517102173
    },
    {
      "id": 8876,
      "name": "Potent Potion of Krait Slaying",
      "icon": "https://render.guildwars2.com/file/FF99ADFCD63FB656C02AFAA80B39063821A77AF9/222640.png",
      "rarity": "Fine",
      "buy": 158,
      "sell": 343,
      "supply": 14697,
      "demand": 19643,
      "unitProfit": 134,
      "marginPct": 84.81012658227847,
      "dailyVolumeEstimate": 14697,
      "score": 353.4256990935735
    },
    {
      "id": 12484,
      "name": "Bowl of Fire Meat Chili",
      "icon": "https://render.guildwars2.com/file/E03C2CA53D4B324379EF5DA85CF3CF547D551F7E/433671.png",
      "rarity": "Fine",
      "buy": 542,
      "sell": 1246,
      "supply": 8519,
      "demand": 5065,
      "unitProfit": 517,
      "marginPct": 95.38745387453874,
      "dailyVolumeEstimate": 5065,
      "score": 353.3785794981534
    },
    {
      "id": 36052,
      "name": "Bowl of Candy Corn Glaze",
      "icon": "https://render.guildwars2.com/file/2ACFBC231FBB3B0DF9920D0800DEDFEB43DBB295/499390.png",
      "rarity": "Basic",
      "buy": 322,
      "sell": 693,
      "supply": 18232,
      "demand": 19556,
      "unitProfit": 267,
      "marginPct": 82.91925465838509,
      "dailyVolumeEstimate": 18232,
      "score": 353.30718050816597
    },
    {
      "id": 20684,
      "name": "Hydrangea Dye",
      "icon": "https://render.guildwars2.com/file/06DF4AD10F92FDC3AB0EA1D8411038D44758BD52/66654.png",
      "rarity": "Fine",
      "buy": 8,
      "sell": 19,
      "supply": 3863,
      "demand": 3252,
      "unitProfit": 8,
      "marginPct": 100,
      "dailyVolumeEstimate": 3252,
      "score": 351.2284063281854
    },
    {
      "id": 38463,
      "name": "Wooden Dagger Skin",
      "icon": "https://render.guildwars2.com/file/FC9C48649C03C6656401A35099CB0A474C37E03D/526325.png",
      "rarity": "Masterwork",
      "buy": 72,
      "sell": 154,
      "supply": 36618,
      "demand": 19320,
      "unitProfit": 59,
      "marginPct": 81.94444444444444,
      "dailyVolumeEstimate": 19320,
      "score": 351.21631448608775
    },
    {
      "id": 12456,
      "name": "Mango Pie",
      "icon": "https://render.guildwars2.com/file/CEF6081FC507AFF365977FB548017169A6BEF065/433646.png",
      "rarity": "Fine",
      "buy": 152,
      "sell": 321,
      "supply": 24107,
      "demand": 26325,
      "unitProfit": 121,
      "marginPct": 79.60526315789474,
      "dailyVolumeEstimate": 24107,
      "score": 348.8430941567769
    },
    {
      "id": 20668,
      "name": "Daffodil Dye",
      "icon": "https://render.guildwars2.com/file/06DF4AD10F92FDC3AB0EA1D8411038D44758BD52/66654.png",
      "rarity": "Fine",
      "buy": 10,
      "sell": 23,
      "supply": 8551,
      "demand": 2943,
      "unitProfit": 10,
      "marginPct": 100,
      "dailyVolumeEstimate": 2943,
      "score": 346.8937805665461
    },
    {
      "id": 24722,
      "name": "Major Rune of the Eagle",
      "icon": "https://render.guildwars2.com/file/B8565FC81408905306730C07E4311309D4F612F0/221072.png",
      "rarity": "Rare",
      "buy": 165,
      "sell": 388,
      "supply": 4813,
      "demand": 2940,
      "unitProfit": 165,
      "marginPct": 100,
      "dailyVolumeEstimate": 2940,
      "score": 346.8495024507069
    },
    {
      "id": 36077,
      "name": "Piece of Candy Corn Almond Brittle",
      "icon": "https://render.guildwars2.com/file/16EBBC48BBAE31E3AEA5AD2C4919CB92AFF8935D/499407.png",
      "rarity": "Fine",
      "buy": 104,
      "sell": 200,
      "supply": 345943,
      "demand": 291592,
      "unitProfit": 66,
      "marginPct": 63.46153846153846,
      "dailyVolumeEstimate": 291592,
      "score": 346.8031617390751
    },
    {
      "id": 24603,
      "name": "Minor Sigil of Geomancy",
      "icon": "https://render.guildwars2.com/file/B4F6FC2ABADE9335543CA4450F33A85F28C157F2/221004.png",
      "rarity": "Masterwork",
      "buy": 103,
      "sell": 224,
      "supply": 10836,
      "demand": 15945,
      "unitProfit": 88,
      "marginPct": 85.43689320388349,
      "dailyVolumeEstimate": 10836,
      "score": 344.73009558870075
    },
    {
      "id": 82991,
      "name": "Bag of Coffee Beans",
      "icon": "https://render.guildwars2.com/file/E322BCBB9975A90974ADE19F6EFD503D767BFEAD/1766608.png",
      "rarity": "Basic",
      "buy": 7,
      "sell": 13,
      "supply": 1069775,
      "demand": 1546111,
      "unitProfit": 4,
      "marginPct": 57.14285714285714,
      "dailyVolumeEstimate": 1069775,
      "score": 344.53102002536826
    },
    {
      "id": 19783,
      "name": "Vital Green Inscription",
      "icon": "https://render.guildwars2.com/file/11C41A3B69CA387A774794060824CBD923A4413A/65987.png",
      "rarity": "Fine",
      "buy": 5,
      "sell": 12,
      "supply": 36779,
      "demand": 2774,
      "unitProfit": 5,
      "marginPct": 100,
      "dailyVolumeEstimate": 2774,
      "score": 344.3262987458695
    },
    {
      "id": 13132,
      "name": "Steel Splint Legging Lining",
      "icon": "https://render.guildwars2.com/file/08DFD908F4572AE030D8C2C9144AC863B65B990B/222846.png",
      "rarity": "Basic",
      "buy": 13,
      "sell": 30,
      "supply": 10207,
      "demand": 5107,
      "unitProfit": 12,
      "marginPct": 92.3076923076923,
      "dailyVolumeEstimate": 5107,
      "score": 342.30008202381947
    },
    {
      "id": 12422,
      "name": "Peach Tart",
      "icon": "https://render.guildwars2.com/file/65026CC17D3BB8B57EF151634B3BFC3505B2DD7A/433616.png",
      "rarity": "Fine",
      "buy": 131,
      "sell": 290,
      "supply": 7840,
      "demand": 10707,
      "unitProfit": 115,
      "marginPct": 87.78625954198473,
      "dailyVolumeEstimate": 7840,
      "score": 341.8723032011201
    },
    {
      "id": 8881,
      "name": "Powerful Potion of Outlaw Slaying",
      "icon": "https://render.guildwars2.com/file/EEB3B79C03ABBFE25E55272967535C5BBD656EB3/220452.png",
      "rarity": "Fine",
      "buy": 163,
      "sell": 356,
      "supply": 9976,
      "demand": 31293,
      "unitProfit": 139,
      "marginPct": 85.2760736196319,
      "dailyVolumeEstimate": 9976,
      "score": 341.0190160357954
    },
    {
      "id": 13122,
      "name": "Iron Pauldron Lining",
      "icon": "https://render.guildwars2.com/file/0095BE7DCDBD5C01AFB99359EE54BD55AAA15198/222880.png",
      "rarity": "Basic",
      "buy": 8,
      "sell": 19,
      "supply": 7340,
      "demand": 2549,
      "unitProfit": 8,
      "marginPct": 100,
      "dailyVolumeEstimate": 2549,
      "score": 340.6540180433955
    },
    {
      "id": 24656,
      "name": "Major Sigil of Ogre Slaying",
      "icon": "https://render.guildwars2.com/file/21DD6D7541FEAB06E890D7AD16E703B207F0690F/221038.png",
      "rarity": "Rare",
      "buy": 151,
      "sell": 346,
      "supply": 7857,
      "demand": 3918,
      "unitProfit": 143,
      "marginPct": 94.70198675496688,
      "dailyVolumeEstimate": 3918,
      "score": 340.2808362101779
    },
    {
      "id": 24561,
      "name": "Superior Sigil of Rage",
      "icon": "https://render.guildwars2.com/file/15310B48271FC15332C65C5E02FEC4FFF298B652/220679.png",
      "rarity": "Exotic",
      "buy": 274,
      "sell": 574,
      "supply": 148063,
      "demand": 22288,
      "unitProfit": 214,
      "marginPct": 78.1021897810219,
      "dailyVolumeEstimate": 22288,
      "score": 339.5953959936027
    },
    {
      "id": 13286,
      "name": "Malachite Copper Stud",
      "icon": "https://render.guildwars2.com/file/E0E02D0F0F9CBBF590392777391AD3E0C5FE706B/340134.png",
      "rarity": "Fine",
      "buy": 43,
      "sell": 99,
      "supply": 3552,
      "demand": 18011,
      "unitProfit": 41,
      "marginPct": 95.34883720930233,
      "dailyVolumeEstimate": 3552,
      "score": 338.545124435029
    },
    {
      "id": 19786,
      "name": "Valkyrie Elder Inscription",
      "icon": "https://render.guildwars2.com/file/7FD7D1B369017FCA36FC7AD52B4DB8B6393630FA/340434.png",
      "rarity": "Fine",
      "buy": 114,
      "sell": 264,
      "supply": 5190,
      "demand": 2925,
      "unitProfit": 111,
      "marginPct": 97.36842105263158,
      "dailyVolumeEstimate": 2925,
      "score": 337.50565764790474
    },
    {
      "id": 12435,
      "name": "Eggplant Fritter",
      "icon": "https://render.guildwars2.com/file/FC0349B80315422CD0749002CDB63CF6402EF1EA/433628.png",
      "rarity": "Fine",
      "buy": 138,
      "sell": 323,
      "supply": 2505,
      "demand": 11555,
      "unitProfit": 137,
      "marginPct": 99.27536231884058,
      "dailyVolumeEstimate": 2505,
      "score": 337.43507690736516
    },
    {
      "id": 8837,
      "name": "Potion of Nightmare Court Slaying",
      "icon": "https://render.guildwars2.com/file/53D7391102534D7F08972842D2E4051078F3A89F/222748.png",
      "rarity": "Fine",
      "buy": 89,
      "sell": 192,
      "supply": 66320,
      "demand": 11412,
      "unitProfit": 74,
      "marginPct": 83.14606741573034,
      "dailyVolumeEstimate": 11412,
      "score": 337.35683873897597
    },
    {
      "id": 12440,
      "name": "Bowl of Mango Salsa",
      "icon": "https://render.guildwars2.com/file/AC01B4B97A67A45263FB2FE2541B774E6B3C020E/433633.png",
      "rarity": "Fine",
      "buy": 136,
      "sell": 300,
      "supply": 6931,
      "demand": 14619,
      "unitProfit": 119,
      "marginPct": 87.5,
      "dailyVolumeEstimate": 6931,
      "score": 336.07512347866447
    },
    {
      "id": 101427,
      "name": "Visage of the Great Dragon Fireworks",
      "icon": "https://render.guildwars2.com/file/794C0F611CB40836A39108DE60C96B3463AABC62/3240050.png",
      "rarity": "Exotic",
      "buy": 269,
      "sell": 568,
      "supply": 49721,
      "demand": 16734,
      "unitProfit": 214,
      "marginPct": 79.5539033457249,
      "dailyVolumeEstimate": 16734,
      "score": 336.0059120343763
    },
    {
      "id": 24693,
      "name": "Minor Rune of the Traveler",
      "icon": "https://render.guildwars2.com/file/94181173FF0DC80CF7F606FEC32E3A741D42646B/221052.png",
      "rarity": "Masterwork",
      "buy": 82,
      "sell": 190,
      "supply": 32278,
      "demand": 3066,
      "unitProfit": 79,
      "marginPct": 96.34146341463415,
      "dailyVolumeEstimate": 3066,
      "score": 335.9151076861175
    },
    {
      "id": 24223,
      "name": "Seraph Badge",
      "icon": "https://render.guildwars2.com/file/CC2E01E0F566A6EEF4F2EC2B19AA7A3E1FEFB1B4/60984.png",
      "rarity": "Basic",
      "buy": 157,
      "sell": 339,
      "supply": 10626,
      "demand": 10558,
      "unitProfit": 131,
      "marginPct": 83.43949044585987,
      "dailyVolumeEstimate": 10558,
      "score": 335.72903533385346
    },
    {
      "id": 12923,
      "name": "Mithril Pistol Barrel",
      "icon": "https://render.guildwars2.com/file/A306ED710CEE2995EE53FB056CDFF7CCF235BF9A/219541.png",
      "rarity": "Basic",
      "buy": 108,
      "sell": 249,
      "supply": 28921,
      "demand": 3056,
      "unitProfit": 104,
      "marginPct": 96.29629629629629,
      "dailyVolumeEstimate": 3056,
      "score": 335.62104224769746
    },
    {
      "id": 71049,
      "name": "Resonating Core",
      "icon": "https://render.guildwars2.com/file/1645711839B36ACF76B5031EE8566A06DB2B020E/1201933.png",
      "rarity": "Basic",
      "buy": 60,
      "sell": 126,
      "supply": 59857,
      "demand": 19058,
      "unitProfit": 47,
      "marginPct": 78.33333333333333,
      "dailyVolumeEstimate": 19058,
      "score": 335.2745086209691
    },
    {
      "id": 12383,
      "name": "Blackberry Cookie",
      "icon": "https://render.guildwars2.com/file/4D78DEA6FA0F95B20CB0D33A9AFDB0A80278BE58/339929.png",
      "rarity": "Fine",
      "buy": 193,
      "sell": 426,
      "supply": 6271,
      "demand": 35714,
      "unitProfit": 169,
      "marginPct": 87.56476683937824,
      "dailyVolumeEstimate": 6271,
      "score": 332.51897533435675
    },
    {
      "id": 9467,
      "name": "Journeyman Tuning Crystal",
      "icon": "https://render.guildwars2.com/file/1F2963C0F8331BC508A2F0E27B3039AC0172E0B9/219369.png",
      "rarity": "Fine",
      "buy": 98,
      "sell": 199,
      "supply": 60396,
      "demand": 38718,
      "unitProfit": 71,
      "marginPct": 72.44897959183673,
      "dailyVolumeEstimate": 38718,
      "score": 332.3904218232622
    },
    {
      "id": 67366,
      "name": "Recipe: Pumpkin Oil",
      "icon": "https://render.guildwars2.com/file/E19734B71C949924A1353106E513DE62729A5313/849374.png",
      "rarity": "Masterwork",
      "buy": 15,
      "sell": 34,
      "supply": 3524,
      "demand": 25511,
      "unitProfit": 14,
      "marginPct": 93.33333333333333,
      "dailyVolumeEstimate": 3524,
      "score": 331.06818465722563
    },
    {
      "id": 12358,
      "name": "Spinach Burger",
      "icon": "https://render.guildwars2.com/file/4B7AC1EC2F70102B07AEE5D47FF049596B651467/433606.png",
      "rarity": "Fine",
      "buy": 142,
      "sell": 296,
      "supply": 20256,
      "demand": 44405,
      "unitProfit": 109,
      "marginPct": 76.76056338028168,
      "dailyVolumeEstimate": 20256,
      "score": 330.5751330721922
    },
    {
      "id": 107078,
      "name": "Visage of the Great Horse Fireworks",
      "icon": "https://render.guildwars2.com/file/3EDF686E07DAD8E550C62C1F7E77094567332269/3744699.png",
      "rarity": "Exotic",
      "buy": 53,
      "sell": 112,
      "supply": 64331,
      "demand": 14350,
      "unitProfit": 42,
      "marginPct": 79.24528301886792,
      "dailyVolumeEstimate": 14350,
      "score": 329.41330359708263
    },
    {
      "id": 8591,
      "name": "Stein of Ancient Dwarven Ale",
      "icon": "https://render.guildwars2.com/file/D92A6B09614BCD0DC5BD30159374C3222A7B5E2D/63101.png",
      "rarity": "Basic",
      "buy": 8,
      "sell": 19,
      "supply": 34352,
      "demand": 1931,
      "unitProfit": 8,
      "marginPct": 100,
      "dailyVolumeEstimate": 1931,
      "score": 328.6007122079475
    },
    {
      "id": 89157,
      "name": "Enhanced Lucent Oil",
      "icon": "https://render.guildwars2.com/file/7B3ADB91E9A87269F11CBBE3E47E9FDE5F5ACFCC/2063491.png",
      "rarity": "Masterwork",
      "buy": 1182,
      "sell": 2679,
      "supply": 3466,
      "demand": 3510,
      "unitProfit": 1095,
      "marginPct": 92.63959390862944,
      "dailyVolumeEstimate": 3466,
      "score": 327.9398863463413
    },
    {
      "id": 62987,
      "name": "Savory Chef's Tools",
      "icon": "https://render.guildwars2.com/file/E2CB1301ECEF0D7DB2A42394F3B4272368A12FE0/866762.png",
      "rarity": "Masterwork",
      "buy": 21,
      "sell": 50,
      "supply": 7856,
      "demand": 1873,
      "unitProfit": 21,
      "marginPct": 100,
      "dailyVolumeEstimate": 1873,
      "score": 327.2769586551759
    },
    {
      "id": 38460,
      "name": "Toy Sword Skin",
      "icon": "https://render.guildwars2.com/file/E24399CBFD53510CDB167AB9D10318D9540626DA/526323.png",
      "rarity": "Masterwork",
      "buy": 86,
      "sell": 174,
      "supply": 39752,
      "demand": 33219,
      "unitProfit": 62,
      "marginPct": 72.09302325581395,
      "dailyVolumeEstimate": 33219,
      "score": 325.9613685385503
    },
    {
      "id": 38296,
      "name": "Recipe: Giver's Mithril Imbued Inscription",
      "icon": "https://render.guildwars2.com/file/A857C2732CCDF31A1B7F4B6654030A1D3E94424F/849388.png",
      "rarity": "Rare",
      "buy": 42,
      "sell": 99,
      "supply": 10750,
      "demand": 1792,
      "unitProfit": 42,
      "marginPct": 100,
      "dailyVolumeEstimate": 1792,
      "score": 325.3580289562183
    },
    {
      "id": 68047,
      "name": "Essence of Time",
      "icon": "https://render.guildwars2.com/file/110F6F3CCE9129BEA23E0D44754630BCECC90838/511850.png",
      "rarity": "Exotic",
      "buy": 182,
      "sell": 376,
      "supply": 24525,
      "demand": 20985,
      "unitProfit": 137,
      "marginPct": 75.27472527472527,
      "dailyVolumeEstimate": 20985,
      "score": 325.3320684550181
    },
    {
      "id": 12917,
      "name": "Mithril Rifle Barrel",
      "icon": "https://render.guildwars2.com/file/7EF14FEDD776037CFC26F7A03798D7F7B36443FB/219540.png",
      "rarity": "Basic",
      "buy": 103,
      "sell": 240,
      "supply": 25318,
      "demand": 2068,
      "unitProfit": 101,
      "marginPct": 98.05825242718447,
      "dailyVolumeEstimate": 2068,
      "score": 325.13767918178564
    },
    {
      "id": 24327,
      "name": "Crystal Fragment",
      "icon": "https://render.guildwars2.com/file/43D43127072CF33D58B25E2FCC940435EB3D4548/66978.png",
      "rarity": "Rare",
      "buy": 188,
      "sell": 396,
      "supply": 13319,
      "demand": 48650,
      "unitProfit": 148,
      "marginPct": 78.72340425531915,
      "dailyVolumeEstimate": 13319,
      "score": 324.695013444401
    },
    {
      "id": 24707,
      "name": "Major Rune of Mercy",
      "icon": "https://render.guildwars2.com/file/769D6A2A4DDD1D666FB3012CE2560963015F9693/221062.png",
      "rarity": "Rare",
      "buy": 178,
      "sell": 414,
      "supply": 2067,
      "demand": 2711,
      "unitProfit": 174,
      "marginPct": 97.75280898876404,
      "dailyVolumeEstimate": 2067,
      "score": 324.104378083939
    },
    {
      "id": 12814,
      "name": "Mithril Setting",
      "icon": "https://render.guildwars2.com/file/EAA5A0126AEFCF9702F4DD41A3DB27AAAC1C48D9/219499.png",
      "rarity": "Basic",
      "buy": 105,
      "sell": 222,
      "supply": 153710,
      "demand": 10916,
      "unitProfit": 84,
      "marginPct": 80,
      "dailyVolumeEstimate": 10916,
      "score": 323.04826482447186
    },
    {
      "id": 24582,
      "name": "Superior Sigil of Life",
      "icon": "https://render.guildwars2.com/file/A7AE0E9D0DF64B69EF309D93E44FFAA90859ABA0/220670.png",
      "rarity": "Exotic",
      "buy": 276,
      "sell": 610,
      "supply": 66665,
      "demand": 4791,
      "unitProfit": 242,
      "marginPct": 87.68115942028986,
      "dailyVolumeEstimate": 4791,
      "score": 322.7119811124144
    },
    {
      "id": 12343,
      "name": "Kastaz Roasted Poultry",
      "icon": "https://render.guildwars2.com/file/12C67B490141660F0034A9D8DCEFCC6EBC0A6143/223193.png",
      "rarity": "Fine",
      "buy": 110,
      "sell": 252,
      "supply": 2588,
      "demand": 5993,
      "unitProfit": 104,
      "marginPct": 94.54545454545455,
      "dailyVolumeEstimate": 2588,
      "score": 322.69612113202425
    },
    {
      "id": 12345,
      "name": "Strawberry Cookie",
      "icon": "https://render.guildwars2.com/file/7F2C5C0BA51605BD3006020AFD2906D4B1D3F942/219435.png",
      "rarity": "Fine",
      "buy": 228,
      "sell": 519,
      "supply": 2841,
      "demand": 18442,
      "unitProfit": 213,
      "marginPct": 93.42105263157895,
      "dailyVolumeEstimate": 2841,
      "score": 322.641196348675
    },
    {
      "id": 24613,
      "name": "Minor Sigil of Force",
      "icon": "https://render.guildwars2.com/file/5F089852CEDA66E947DC14B70661F806CAFD0D01/221010.png",
      "rarity": "Masterwork",
      "buy": 117,
      "sell": 250,
      "supply": 13509,
      "demand": 8937,
      "unitProfit": 95,
      "marginPct": 81.19658119658119,
      "dailyVolumeEstimate": 8937,
      "score": 320.82720793231823
    },
    {
      "id": 8846,
      "name": "Potion of Krait Slaying",
      "icon": "https://render.guildwars2.com/file/A6CB53C4202BE165296F1296AD5C68CB1297D5FD/222760.png",
      "rarity": "Fine",
      "buy": 612,
      "sell": 1342,
      "supply": 5112,
      "demand": 9250,
      "unitProfit": 529,
      "marginPct": 86.43790849673204,
      "dailyVolumeEstimate": 5112,
      "score": 320.57017881574154
    },
    {
      "id": 19846,
      "name": "Carrion Elder Inscription",
      "icon": "https://render.guildwars2.com/file/E46C654CBF039030E33768F46B576595E3BFF163/66030.png",
      "rarity": "Fine",
      "buy": 116,
      "sell": 260,
      "supply": 5624,
      "demand": 3455,
      "unitProfit": 105,
      "marginPct": 90.51724137931035,
      "dailyVolumeEstimate": 3455,
      "score": 320.3019328014826
    },
    {
      "id": 12829,
      "name": "Silver Band",
      "icon": "https://render.guildwars2.com/file/F01AAF097A1DD7E506B991093308F304BE93CDE2/63398.png",
      "rarity": "Basic",
      "buy": 28,
      "sell": 64,
      "supply": 7857,
      "demand": 2095,
      "unitProfit": 27,
      "marginPct": 96.42857142857143,
      "dailyVolumeEstimate": 2095,
      "score": 320.27701612291287
    },
    {
      "id": 9366,
      "name": "Tiny Moldy Bag",
      "icon": "https://render.guildwars2.com/file/EBC5CEC199D1E51B02756A1C796A65E9D24F04B5/63171.png",
      "rarity": "Basic",
      "buy": 57,
      "sell": 120,
      "supply": 11267,
      "demand": 11793,
      "unitProfit": 45,
      "marginPct": 78.94736842105263,
      "dailyVolumeEstimate": 11267,
      "score": 319.8826451300318
    },
    {
      "id": 12139,
      "name": "Bowl of Front Line Stew",
      "icon": "https://render.guildwars2.com/file/1F0595F2252BEFA1396235A0A56DFD499C95D455/63085.png",
      "rarity": "Basic",
      "buy": 128,
      "sell": 300,
      "supply": 1671,
      "demand": 5493,
      "unitProfit": 127,
      "marginPct": 99.21875,
      "dailyVolumeEstimate": 1671,
      "score": 319.80547397193806
    }
  ]
}