{
  "generatedAt": "2026-06-26T11:27:35.812Z",
  "count": 100,
  "tips": [
    {
      "id": 77648,
      "name": "Cup of Spiced Apple Cider",
      "icon": "https://render.guildwars2.com/file/36E9EEE30906BD0AB100092D2120C6326CABF8B5/1322536.png",
      "rarity": "Basic",
      "buy": 6,
      "sell": 14,
      "supply": 5088963,
      "demand": 1416116,
      "unitProfit": 6,
      "marginPct": 100,
      "dailyVolumeEstimate": 1416116,
      "score": 615.1099136372998
    },
    {
      "id": 43909,
      "name": "Lightning Catcher Skin",
      "icon": "https://render.guildwars2.com/file/0CFBB03794F5D8DE9099267EB6F9E3BD0EDA229A/603282.png",
      "rarity": "Rare",
      "buy": 7,
      "sell": 17,
      "supply": 117588,
      "demand": 150776,
      "unitProfit": 7,
      "marginPct": 100,
      "dailyVolumeEstimate": 117588,
      "score": 507.03666970569554
    },
    {
      "id": 12271,
      "name": "Bottle of Soy Sauce",
      "icon": "https://render.guildwars2.com/file/E745C51C0D067B030A6629C80A9B08A4B0146556/63083.png",
      "rarity": "Basic",
      "buy": 4,
      "sell": 10,
      "supply": 105527,
      "demand": 38853,
      "unitProfit": 4,
      "marginPct": 100,
      "dailyVolumeEstimate": 38853,
      "score": 458.9435735839732
    },
    {
      "id": 12184,
      "name": "Cup of Potato Fries",
      "icon": "https://render.guildwars2.com/file/4203F100A83AB50D055F0279A650AEF22E5E2B6E/63280.png",
      "rarity": "Basic",
      "buy": 25,
      "sell": 57,
      "supply": 82300,
      "demand": 87800,
      "unitProfit": 23,
      "marginPct": 92,
      "dailyVolumeEstimate": 82300,
      "score": 452.2172703176527
    },
    {
      "id": 36047,
      "name": "Recipe: Major Rune of the Mad King",
      "icon": "https://render.guildwars2.com/file/7725EEB5EE0E4905B6193F2B2507E7C004A2D6EA/849264.png",
      "rarity": "Rare",
      "buy": 2,
      "sell": 6,
      "supply": 24038,
      "demand": 19507,
      "unitProfit": 2,
      "marginPct": 100,
      "dailyVolumeEstimate": 19507,
      "score": 429.02127469195284
    },
    {
      "id": 19758,
      "name": "Green Wood Dowel",
      "icon": "https://render.guildwars2.com/file/0C6871D2069E2C074A93E205C9C7097DBF0E9D13/65963.png",
      "rarity": "Fine",
      "buy": 9,
      "sell": 21,
      "supply": 377056,
      "demand": 16606,
      "unitProfit": 9,
      "marginPct": 100,
      "dailyVolumeEstimate": 16606,
      "score": 422.0291185665156
    },
    {
      "id": 9372,
      "name": "Large Moldy Bag",
      "icon": "https://render.guildwars2.com/file/EBC5CEC199D1E51B02756A1C796A65E9D24F04B5/63171.png",
      "rarity": "Basic",
      "buy": 76,
      "sell": 177,
      "supply": 27570,
      "demand": 18593,
      "unitProfit": 74,
      "marginPct": 97.36842105263158,
      "dailyVolumeEstimate": 18593,
      "score": 415.7020910132849
    },
    {
      "id": 12990,
      "name": "Bronze Plated Dowel",
      "icon": "https://render.guildwars2.com/file/1A34B1613F19C19997F40295A37E5AD902BB0F31/63487.png",
      "rarity": "Masterwork",
      "buy": 79,
      "sell": 183,
      "supply": 17244,
      "demand": 35529,
      "unitProfit": 77,
      "marginPct": 97.46835443037975,
      "dailyVolumeEstimate": 17244,
      "score": 412.94059025337026
    },
    {
      "id": 36074,
      "name": "Bowl of Candy Corn Custard",
      "icon": "https://render.guildwars2.com/file/21B563FEFA9FA405B5B50C6E1704007F0B2408B6/499404.png",
      "rarity": "Fine",
      "buy": 30,
      "sell": 60,
      "supply": 742524,
      "demand": 3191067,
      "unitProfit": 21,
      "marginPct": 70,
      "dailyVolumeEstimate": 742524,
      "score": 410.9497756317037
    },
    {
      "id": 68438,
      "name": "Minor Rune of Snowfall",
      "icon": "https://render.guildwars2.com/file/32AF4174DAB764C231E3C4AA6056CA585F79D998/924727.png",
      "rarity": "Masterwork",
      "buy": 102,
      "sell": 229,
      "supply": 29735,
      "demand": 74567,
      "unitProfit": 93,
      "marginPct": 91.17647058823529,
      "dailyVolumeEstimate": 29735,
      "score": 407.8581146785816
    },
    {
      "id": 24301,
      "name": "Charged Sliver",
      "icon": "https://render.guildwars2.com/file/3E2CD04924CFA55FEBF9614DA490D7AE660C1D24/66956.png",
      "rarity": "Rare",
      "buy": 26,
      "sell": 58,
      "supply": 40640,
      "demand": 56920,
      "unitProfit": 23,
      "marginPct": 88.46153846153845,
      "dailyVolumeEstimate": 40640,
      "score": 407.7160802579238
    },
    {
      "id": 36106,
      "name": "Endless Halloween Tonic",
      "icon": "https://render.guildwars2.com/file/3313DA0547A14A1AC5BE4076FEFD275519E8DF0E/499418.png",
      "rarity": "Exotic",
      "buy": 19,
      "sell": 44,
      "supply": 31613,
      "demand": 11663,
      "unitProfit": 19,
      "marginPct": 100,
      "dailyVolumeEstimate": 11663,
      "score": 406.68475109738995
    },
    {
      "id": 8887,
      "name": "Powerful Potion of Inquest Slaying",
      "icon": "https://render.guildwars2.com/file/72E638C510AC04A068DDBC3C7B3C49D1A860C114/222670.png",
      "rarity": "Fine",
      "buy": 259,
      "sell": 581,
      "supply": 34187,
      "demand": 29068,
      "unitProfit": 235,
      "marginPct": 90.73359073359073,
      "dailyVolumeEstimate": 29068,
      "score": 404.98303922670215
    },
    {
      "id": 70714,
      "name": "Sheet of Fine Paper",
      "icon": "https://render.guildwars2.com/file/674D5BE1181B05FB64B638FD4702DC7CCBB4060F/1201916.png",
      "rarity": "Fine",
      "buy": 199,
      "sell": 459,
      "supply": 25219,
      "demand": 15212,
      "unitProfit": 191,
      "marginPct": 95.97989949748744,
      "dailyVolumeEstimate": 15212,
      "score": 401.40856244527606
    },
    {
      "id": 38460,
      "name": "Toy Sword Skin",
      "icon": "https://render.guildwars2.com/file/E24399CBFD53510CDB167AB9D10318D9540626DA/526323.png",
      "rarity": "Masterwork",
      "buy": 78,
      "sell": 173,
      "supply": 39351,
      "demand": 32740,
      "unitProfit": 69,
      "marginPct": 88.46153846153845,
      "dailyVolumeEstimate": 32740,
      "score": 399.41197929211626
    },
    {
      "id": 21669,
      "name": "Shredded Garment",
      "icon": "https://render.guildwars2.com/file/F7671068669C954C4636BA62061534AF4625974B/223681.png",
      "rarity": "Basic",
      "buy": 15,
      "sell": 34,
      "supply": 18818,
      "demand": 20580,
      "unitProfit": 14,
      "marginPct": 93.33333333333333,
      "dailyVolumeEstimate": 18818,
      "score": 398.9623439439863
    },
    {
      "id": 12992,
      "name": "Steel Plated Dowel",
      "icon": "https://render.guildwars2.com/file/D87B1BB6BE69A3B90FBFD0D8E9AC5F0861FB7DF8/63489.png",
      "rarity": "Masterwork",
      "buy": 267,
      "sell": 621,
      "supply": 44815,
      "demand": 12022,
      "unitProfit": 261,
      "marginPct": 97.75280898876404,
      "dailyVolumeEstimate": 12022,
      "score": 398.83271651504464
    },
    {
      "id": 24303,
      "name": "Charged Shard",
      "icon": "https://render.guildwars2.com/file/306AB62DEBCD6D02113CD0730BDC6F95BA9B9AC4/65587.png",
      "rarity": "Rare",
      "buy": 97,
      "sell": 208,
      "supply": 93981,
      "demand": 58416,
      "unitProfit": 80,
      "marginPct": 82.4742268041237,
      "dailyVolumeEstimate": 58416,
      "score": 393.1166391797537
    },
    {
      "id": 86964,
      "name": "Visage of the Great Dog Firework",
      "icon": "https://render.guildwars2.com/file/9E49C0AFB4935DC92DDD2F7C536A59031EB35BE6/1938439.png",
      "rarity": "Exotic",
      "buy": 515,
      "sell": 1200,
      "supply": 50774,
      "demand": 9960,
      "unitProfit": 505,
      "marginPct": 98.05825242718447,
      "dailyVolumeEstimate": 9960,
      "score": 392.0665989805366
    },
    {
      "id": 8888,
      "name": "Powerful Potion of Ogre Slaying",
      "icon": "https://render.guildwars2.com/file/0607283F99092FE46F001E337A4D2148DAD1B480/222680.png",
      "rarity": "Fine",
      "buy": 150,
      "sell": 336,
      "supply": 77651,
      "demand": 20509,
      "unitProfit": 135,
      "marginPct": 90,
      "dailyVolumeEstimate": 20509,
      "score": 388.07690943315293
    },
    {
      "id": 12536,
      "name": "Mint Leaf",
      "icon": "https://render.guildwars2.com/file/2D0726C61FBA172F6B96E3BF91420ACED83FB554/219484.png",
      "rarity": "Basic",
      "buy": 9,
      "sell": 19,
      "supply": 324008,
      "demand": 93302,
      "unitProfit": 7,
      "marginPct": 77.77777777777779,
      "dailyVolumeEstimate": 93302,
      "score": 386.54743617581704
    },
    {
      "id": 24552,
      "name": "Minor Sigil of Air",
      "icon": "https://render.guildwars2.com/file/AEA3A8CE6023B90761711CBC981732356AD00205/220976.png",
      "rarity": "Masterwork",
      "buy": 130,
      "sell": 299,
      "supply": 19734,
      "demand": 10996,
      "unitProfit": 124,
      "marginPct": 95.38461538461539,
      "dailyVolumeEstimate": 10996,
      "score": 385.47538762055734
    },
    {
      "id": 19932,
      "name": "Rejuvenating Cotton Insignia",
      "icon": "https://render.guildwars2.com/file/4BC33F96D573ECD7B7DB36275D1E6993D3473672/340505.png",
      "rarity": "Fine",
      "buy": 452,
      "sell": 1038,
      "supply": 12108,
      "demand": 10331,
      "unitProfit": 430,
      "marginPct": 95.13274336283186,
      "dailyVolumeEstimate": 10331,
      "score": 381.88037409857304
    },
    {
      "id": 8890,
      "name": "Powerful Potion of Grawl Slaying",
      "icon": "https://render.guildwars2.com/file/D8AEFEEE53CE4A3B32EE65E52B910F3BC53EF26B/222668.png",
      "rarity": "Fine",
      "buy": 180,
      "sell": 400,
      "supply": 20146,
      "demand": 18615,
      "unitProfit": 160,
      "marginPct": 88.88888888888889,
      "dailyVolumeEstimate": 18615,
      "score": 379.54545513588204
    },
    {
      "id": 12304,
      "name": "Filet of Sesame-Roasted Meat",
      "icon": "https://render.guildwars2.com/file/7DB0CCA51EBEB995FDECF919FD4CEDE1E1521E0B/339908.png",
      "rarity": "Fine",
      "buy": 172,
      "sell": 387,
      "supply": 16556,
      "demand": 14349,
      "unitProfit": 157,
      "marginPct": 91.27906976744185,
      "dailyVolumeEstimate": 14349,
      "score": 379.43357469069286
    },
    {
      "id": 24234,
      "name": "Piece of Charr Scrap Metal",
      "icon": "https://render.guildwars2.com/file/D9C8AAED4B80010B809E465D90E81634D62EEF16/63137.png",
      "rarity": "Basic",
      "buy": 46,
      "sell": 99,
      "supply": 138284,
      "demand": 39062,
      "unitProfit": 38,
      "marginPct": 82.6086956521739,
      "dailyVolumeEstimate": 39062,
      "score": 379.3197664296386
    },
    {
      "id": 68439,
      "name": "Minor Sigil of Mischief",
      "icon": "https://render.guildwars2.com/file/B43EFAD8ED47F27BC22343935F4F01F167240832/924728.png",
      "rarity": "Masterwork",
      "buy": 121,
      "sell": 266,
      "supply": 21917,
      "demand": 21013,
      "unitProfit": 105,
      "marginPct": 86.77685950413223,
      "dailyVolumeEstimate": 21013,
      "score": 375.09373258823
    },
    {
      "id": 101427,
      "name": "Visage of the Great Dragon Fireworks",
      "icon": "https://render.guildwars2.com/file/794C0F611CB40836A39108DE60C96B3463AABC62/3240050.png",
      "rarity": "Exotic",
      "buy": 262,
      "sell": 583,
      "supply": 49869,
      "demand": 15475,
      "unitProfit": 234,
      "marginPct": 89.31297709923665,
      "dailyVolumeEstimate": 15475,
      "score": 374.19089340668495
    },
    {
      "id": 19813,
      "name": "Strong Cotton Insignia",
      "icon": "https://render.guildwars2.com/file/CC09F313AC1E0A175F753E25B22BD927F4923154/340437.png",
      "rarity": "Fine",
      "buy": 473,
      "sell": 1065,
      "supply": 13064,
      "demand": 11482,
      "unitProfit": 432,
      "marginPct": 91.33192389006342,
      "dailyVolumeEstimate": 11482,
      "score": 370.81266756962646
    },
    {
      "id": 12312,
      "name": "Strawberry Tart",
      "icon": "https://render.guildwars2.com/file/74EF534A089C02C140EC777E0BF0A5A06B0457A7/63353.png",
      "rarity": "Fine",
      "buy": 156,
      "sell": 352,
      "supply": 11094,
      "demand": 71876,
      "unitProfit": 143,
      "marginPct": 91.66666666666666,
      "dailyVolumeEstimate": 11094,
      "score": 370.8033364354024
    },
    {
      "id": 12737,
      "name": "Grilled Steak",
      "icon": "https://render.guildwars2.com/file/A60F6A14B6BCBFF7D6FA227C5EB1C4514ECA4C4D/63132.png",
      "rarity": "Fine",
      "buy": 199,
      "sell": 467,
      "supply": 4980,
      "demand": 5639,
      "unitProfit": 198,
      "marginPct": 99.49748743718592,
      "dailyVolumeEstimate": 4980,
      "score": 367.8737061623175
    },
    {
      "id": 36077,
      "name": "Piece of Candy Corn Almond Brittle",
      "icon": "https://render.guildwars2.com/file/16EBBC48BBAE31E3AEA5AD2C4919CB92AFF8935D/499407.png",
      "rarity": "Fine",
      "buy": 102,
      "sell": 200,
      "supply": 337129,
      "demand": 307490,
      "unitProfit": 68,
      "marginPct": 66.66666666666666,
      "dailyVolumeEstimate": 307490,
      "score": 365.8554939244939
    },
    {
      "id": 12395,
      "name": "Plate of Roast Meat with Mint Sauce",
      "icon": "https://render.guildwars2.com/file/36609A67BC083AAD66B9F199735AFF6BCC0B6641/339941.png",
      "rarity": "Fine",
      "buy": 140,
      "sell": 325,
      "supply": 5812,
      "demand": 31479,
      "unitProfit": 136,
      "marginPct": 97.14285714285714,
      "dailyVolumeEstimate": 5812,
      "score": 365.6846028014777
    },
    {
      "id": 8843,
      "name": "Potion of Ogre Slaying",
      "icon": "https://render.guildwars2.com/file/3D38351333F30318CA5A5E0E28DDAF6EAA5D35EA/222762.png",
      "rarity": "Fine",
      "buy": 407,
      "sell": 899,
      "supply": 20004,
      "demand": 14620,
      "unitProfit": 357,
      "marginPct": 87.71498771498771,
      "dailyVolumeEstimate": 14620,
      "score": 365.3309131519868
    },
    {
      "id": 12384,
      "name": "Pumpkin Pie",
      "icon": "https://render.guildwars2.com/file/0FE8690B0A50A1235B0A421D1B54E30AA60AE2DD/339930.png",
      "rarity": "Fine",
      "buy": 124,
      "sell": 275,
      "supply": 13937,
      "demand": 31562,
      "unitProfit": 109,
      "marginPct": 87.90322580645162,
      "dailyVolumeEstimate": 13937,
      "score": 364.2885888387442
    },
    {
      "id": 8579,
      "name": "Stein of Hunter's Ale",
      "icon": "https://render.guildwars2.com/file/5B6A00A7056C0DC8DA7448C0B1FC07560C6AD5B7/63092.png",
      "rarity": "Basic",
      "buy": 8,
      "sell": 19,
      "supply": 93842,
      "demand": 4320,
      "unitProfit": 8,
      "marginPct": 100,
      "dailyVolumeEstimate": 4320,
      "score": 363.558426631123
    },
    {
      "id": 12353,
      "name": "Bowl of Simple Meat Chili",
      "icon": "https://render.guildwars2.com/file/3B4AC7EA53242D926C64751F7FD2F90BC1BEDA41/433603.png",
      "rarity": "Fine",
      "buy": 33,
      "sell": 75,
      "supply": 9937,
      "demand": 17294,
      "unitProfit": 30,
      "marginPct": 90.9090909090909,
      "dailyVolumeEstimate": 9937,
      "score": 363.390817491774
    },
    {
      "id": 36052,
      "name": "Bowl of Candy Corn Glaze",
      "icon": "https://render.guildwars2.com/file/2ACFBC231FBB3B0DF9920D0800DEDFEB43DBB295/499390.png",
      "rarity": "Basic",
      "buy": 308,
      "sell": 670,
      "supply": 19708,
      "demand": 18318,
      "unitProfit": 261,
      "marginPct": 84.74025974025975,
      "dailyVolumeEstimate": 18318,
      "score": 361.2394026145227
    },
    {
      "id": 24331,
      "name": "Pile of Soiled Essence",
      "icon": "https://render.guildwars2.com/file/40AD50C4C1AABB0562B9F1E6051267F05A344840/434538.png",
      "rarity": "Rare",
      "buy": 66,
      "sell": 141,
      "supply": 24931,
      "demand": 63993,
      "unitProfit": 54,
      "marginPct": 81.81818181818183,
      "dailyVolumeEstimate": 24931,
      "score": 359.73467330890594
    },
    {
      "id": 9467,
      "name": "Journeyman Tuning Crystal",
      "icon": "https://render.guildwars2.com/file/1F2963C0F8331BC508A2F0E27B3039AC0172E0B9/219369.png",
      "rarity": "Fine",
      "buy": 97,
      "sell": 203,
      "supply": 60561,
      "demand": 38545,
      "unitProfit": 76,
      "marginPct": 78.35051546391753,
      "dailyVolumeEstimate": 38545,
      "score": 359.3138433991152
    },
    {
      "id": 46688,
      "name": "Soldier's Orichalcum Imbued Inscription",
      "icon": "https://render.guildwars2.com/file/4B69327AC17E3A225E732F0FE6EE205B0F0B17ED/631476.png",
      "rarity": "Exotic",
      "buy": 533,
      "sell": 1198,
      "supply": 13896,
      "demand": 7796,
      "unitProfit": 485,
      "marginPct": 90.99437148217636,
      "dailyVolumeEstimate": 7796,
      "score": 354.1434998305868
    },
    {
      "id": 12289,
      "name": "Lemon Bar",
      "icon": "https://render.guildwars2.com/file/A74CD6C6DB585227BD266920AD1BC936DB0D07D2/339902.png",
      "rarity": "Fine",
      "buy": 118,
      "sell": 249,
      "supply": 26495,
      "demand": 37718,
      "unitProfit": 94,
      "marginPct": 79.66101694915254,
      "dailyVolumeEstimate": 26495,
      "score": 352.3550420507202
    },
    {
      "id": 20727,
      "name": "Spring Dew Dye",
      "icon": "https://render.guildwars2.com/file/4C6A69A2F750523C239A075656E719ED07492B2E/66652.png",
      "rarity": "Fine",
      "buy": 8,
      "sell": 19,
      "supply": 3170,
      "demand": 5770,
      "unitProfit": 8,
      "marginPct": 100,
      "dailyVolumeEstimate": 3170,
      "score": 350.1196242027089
    },
    {
      "id": 36094,
      "name": "Potent Potion of Halloween Slaying",
      "icon": "https://render.guildwars2.com/file/76CFFE3E686A3F03E5571890F903221E9719EACE/222642.png",
      "rarity": "Fine",
      "buy": 147,
      "sell": 334,
      "supply": 5622,
      "demand": 20954,
      "unitProfit": 137,
      "marginPct": 93.19727891156462,
      "dailyVolumeEstimate": 5622,
      "score": 349.4868213882913
    },
    {
      "id": 24723,
      "name": "Superior Rune of the Eagle",
      "icon": "https://render.guildwars2.com/file/2966CB3D97E85EB0E4C33AFB6D1FB63D7304EC97/220700.png",
      "rarity": "Exotic",
      "buy": 703,
      "sell": 1625,
      "supply": 33952,
      "demand": 4187,
      "unitProfit": 678,
      "marginPct": 96.44381223328593,
      "dailyVolumeEstimate": 4187,
      "score": 349.32013147917695
    },
    {
      "id": 24573,
      "name": "Minor Sigil of Bloodlust",
      "icon": "https://render.guildwars2.com/file/2BE192D72AD8F3DF06AA54FD12066960A349C8F2/220988.png",
      "rarity": "Masterwork",
      "buy": 136,
      "sell": 300,
      "supply": 9312,
      "demand": 15803,
      "unitProfit": 119,
      "marginPct": 87.5,
      "dailyVolumeEstimate": 9312,
      "score": 347.2953402585556
    },
    {
      "id": 24657,
      "name": "Minor Sigil of Ogre Slaying",
      "icon": "https://render.guildwars2.com/file/CE6A7BE1466F637BC4A0DD24ECC960543403FABB/221039.png",
      "rarity": "Masterwork",
      "buy": 111,
      "sell": 249,
      "supply": 21889,
      "demand": 6466,
      "unitProfit": 101,
      "marginPct": 90.990990990991,
      "dailyVolumeEstimate": 6466,
      "score": 346.7396296897827
    },
    {
      "id": 12194,
      "name": "Slice of Garlic Bread",
      "icon": "https://render.guildwars2.com/file/2E369579E06AB0DD93A246E06D5CE5D1BF0AF112/219406.png",
      "rarity": "Fine",
      "buy": 95,
      "sell": 208,
      "supply": 11027,
      "demand": 10226,
      "unitProfit": 82,
      "marginPct": 86.31578947368422,
      "dailyVolumeEstimate": 10226,
      "score": 346.1045863029278
    },
    {
      "id": 13167,
      "name": "Orichalcum Helmet Casing",
      "icon": "https://render.guildwars2.com/file/98E23622A2743AAD6FA27F377934B6C9B39BBD56/219606.png",
      "rarity": "Basic",
      "buy": 311,
      "sell": 713,
      "supply": 4410,
      "demand": 5614,
      "unitProfit": 295,
      "marginPct": 94.85530546623794,
      "dailyVolumeEstimate": 4410,
      "score": 345.7036758985949
    },
    {
      "id": 68625,
      "name": "Lunar New Year Firework",
      "icon": "https://render.guildwars2.com/file/3977630B7C0CE9EBA563177AD39A911893047DE7/947643.png",
      "rarity": "Masterwork",
      "buy": 1187,
      "sell": 2587,
      "supply": 11284,
      "demand": 18797,
      "unitProfit": 1012,
      "marginPct": 85.25695029486099,
      "dailyVolumeEstimate": 11284,
      "score": 345.50392436181517
    },
    {
      "id": 12157,
      "name": "Jar of Vinegar",
      "icon": "https://render.guildwars2.com/file/116B302CC6143B753304B771760EB9735918B4FB/63102.png",
      "rarity": "Basic",
      "buy": 6,
      "sell": 12,
      "supply": 151778,
      "demand": 164546,
      "unitProfit": 4,
      "marginPct": 66.66666666666666,
      "dailyVolumeEstimate": 151778,
      "score": 345.41411247593555
    },
    {
      "id": 19840,
      "name": "Rampager's Hard Inscription",
      "icon": "https://render.guildwars2.com/file/B41A05563ECE6C0A4299089949B30567EE0864EE/66024.png",
      "rarity": "Fine",
      "buy": 516,
      "sell": 1150,
      "supply": 8384,
      "demand": 7282,
      "unitProfit": 461,
      "marginPct": 89.34108527131784,
      "dailyVolumeEstimate": 7282,
      "score": 345.0629947459145
    },
    {
      "id": 20720,
      "name": "Sea Breeze Dye",
      "icon": "https://render.guildwars2.com/file/4C6A69A2F750523C239A075656E719ED07492B2E/66652.png",
      "rarity": "Fine",
      "buy": 7,
      "sell": 17,
      "supply": 3159,
      "demand": 2506,
      "unitProfit": 7,
      "marginPct": 100,
      "dailyVolumeEstimate": 2506,
      "score": 339.91543339582165
    },
    {
      "id": 12811,
      "name": "Silver Hook",
      "icon": "https://render.guildwars2.com/file/7472449776AA61ABABA4FB3867F354DB5955E2EE/63392.png",
      "rarity": "Basic",
      "buy": 30,
      "sell": 70,
      "supply": 3239,
      "demand": 5763,
      "unitProfit": 29,
      "marginPct": 96.66666666666667,
      "dailyVolumeEstimate": 3239,
      "score": 339.3526843199725
    },
    {
      "id": 8879,
      "name": "Powerful Potion of Flame Legion Slaying",
      "icon": "https://render.guildwars2.com/file/11CF3D6BF000C19FFAD9800A0B01080B5149A1D0/222674.png",
      "rarity": "Fine",
      "buy": 195,
      "sell": 414,
      "supply": 14482,
      "demand": 22423,
      "unitProfit": 157,
      "marginPct": 80.51282051282051,
      "dailyVolumeEstimate": 14482,
      "score": 335.00245605987624
    },
    {
      "id": 8841,
      "name": "Potion of Demon Slaying",
      "icon": "https://render.guildwars2.com/file/6D41597AEC924EE557A8E0D0AFF655D04CEB0D14/222696.png",
      "rarity": "Fine",
      "buy": 544,
      "sell": 1195,
      "supply": 17591,
      "demand": 7373,
      "unitProfit": 471,
      "marginPct": 86.58088235294117,
      "dailyVolumeEstimate": 7373,
      "score": 334.86914995776027
    },
    {
      "id": 24721,
      "name": "Minor Rune of the Eagle",
      "icon": "https://render.guildwars2.com/file/A46D7A04B79BC40141929FF9B1C2FAFA2A7F4025/221071.png",
      "rarity": "Masterwork",
      "buy": 80,
      "sell": 171,
      "supply": 22177,
      "demand": 12786,
      "unitProfit": 65,
      "marginPct": 81.25,
      "dailyVolumeEstimate": 12786,
      "score": 333.6749540456155
    },
    {
      "id": 36835,
      "name": "Stuffed Artichoke with Tropical Dressing",
      "icon": "https://render.guildwars2.com/file/5B69CE717C6CBC5B52B33A2B66B2A50F74331138/511789.png",
      "rarity": "Fine",
      "buy": 231,
      "sell": 515,
      "supply": 5730,
      "demand": 5459,
      "unitProfit": 206,
      "marginPct": 89.17748917748918,
      "dailyVolumeEstimate": 5459,
      "score": 333.2734564489939
    },
    {
      "id": 12911,
      "name": "Mithril Shield Boss",
      "icon": "https://render.guildwars2.com/file/646A063293DDC536B02C0C64D83A0201DC26779B/219539.png",
      "rarity": "Basic",
      "buy": 102,
      "sell": 229,
      "supply": 4517,
      "demand": 7695,
      "unitProfit": 93,
      "marginPct": 91.17647058823529,
      "dailyVolumeEstimate": 4517,
      "score": 333.245097129749
    },
    {
      "id": 12522,
      "name": "Orange Cake",
      "icon": "https://render.guildwars2.com/file/AB6CAD0C34ED55015096EB59C6DF0CA6BE411204/339961.png",
      "rarity": "Fine",
      "buy": 121,
      "sell": 267,
      "supply": 6344,
      "demand": 30522,
      "unitProfit": 106,
      "marginPct": 87.60330578512396,
      "dailyVolumeEstimate": 6344,
      "score": 333.10558049723693
    },
    {
      "id": 19792,
      "name": "Spool of Jute Thread",
      "icon": "https://render.guildwars2.com/file/C7C2E54962F3A20745FF94DFBC1BFF11CF9DEA5E/65994.png",
      "rarity": "Basic",
      "buy": 6,
      "sell": 12,
      "supply": 261548,
      "demand": 97100,
      "unitProfit": 4,
      "marginPct": 66.66666666666666,
      "dailyVolumeEstimate": 97100,
      "score": 332.4815801691128
    },
    {
      "id": 12386,
      "name": "Bowl of Blackberry Pear Compote",
      "icon": "https://render.guildwars2.com/file/C4ABFE75D5463C22030EF97012D89D5E94D1DAF8/339932.png",
      "rarity": "Fine",
      "buy": 110,
      "sell": 231,
      "supply": 25002,
      "demand": 17182,
      "unitProfit": 86,
      "marginPct": 78.18181818181819,
      "dailyVolumeEstimate": 17182,
      "score": 331.10773922560435
    },
    {
      "id": 75862,
      "name": "Pouch of White Pigment",
      "icon": "https://render.guildwars2.com/file/E20809A539CF3813A92E6832734053F579673FDE/1200715.png",
      "rarity": "Fine",
      "buy": 64,
      "sell": 127,
      "supply": 437739,
      "demand": 62863,
      "unitProfit": 44,
      "marginPct": 68.75,
      "dailyVolumeEstimate": 62863,
      "score": 329.8901382884065
    },
    {
      "id": 12324,
      "name": "Bag of Starch",
      "icon": "https://render.guildwars2.com/file/13282DF437062E48247991635590CF53BB340B5E/63361.png",
      "rarity": "Basic",
      "buy": 7,
      "sell": 15,
      "supply": 40748,
      "demand": 151325,
      "unitProfit": 5,
      "marginPct": 71.42857142857143,
      "dailyVolumeEstimate": 40748,
      "score": 329.29406824370915
    },
    {
      "id": 8591,
      "name": "Stein of Ancient Dwarven Ale",
      "icon": "https://render.guildwars2.com/file/D92A6B09614BCD0DC5BD30159374C3222A7B5E2D/63101.png",
      "rarity": "Basic",
      "buy": 8,
      "sell": 19,
      "supply": 34670,
      "demand": 1931,
      "unitProfit": 8,
      "marginPct": 100,
      "dailyVolumeEstimate": 1931,
      "score": 328.6007122079475
    },
    {
      "id": 12457,
      "name": "Omnomberry Pie",
      "icon": "https://render.guildwars2.com/file/52C5B55D04BE1629326334CAA905D8B6D6F02940/433647.png",
      "rarity": "Fine",
      "buy": 262,
      "sell": 595,
      "supply": 8120,
      "demand": 3468,
      "unitProfit": 243,
      "marginPct": 92.74809160305344,
      "dailyVolumeEstimate": 3468,
      "score": 328.347192695275
    },
    {
      "id": 12227,
      "name": "Sugar Cookie",
      "icon": "https://render.guildwars2.com/file/A7634E30EF3F601E30ECFFC33760DB28E63A7DF1/63151.png",
      "rarity": "Fine",
      "buy": 76,
      "sell": 175,
      "supply": 2907,
      "demand": 9629,
      "unitProfit": 72,
      "marginPct": 94.73684210526315,
      "dailyVolumeEstimate": 2907,
      "score": 328.1299959966631
    },
    {
      "id": 77750,
      "name": "Lucky Draketail",
      "icon": "https://render.guildwars2.com/file/B00E4AB7E79F5F73DCBD0B33D5ABA967A0F15824/1341436.png",
      "rarity": "Masterwork",
      "buy": 10,
      "sell": 18,
      "supply": 3649587,
      "demand": 14480166,
      "unitProfit": 5,
      "marginPct": 50,
      "dailyVolumeEstimate": 3649587,
      "score": 328.11219199781306
    },
    {
      "id": 12187,
      "name": "Slice of Buttered Toast",
      "icon": "https://render.guildwars2.com/file/C42F031F7AF1B4766D5B0404392C9B2026B760E8/63283.png",
      "rarity": "Basic",
      "buy": 27,
      "sell": 60,
      "supply": 16294,
      "demand": 4848,
      "unitProfit": 24,
      "marginPct": 88.88888888888889,
      "dailyVolumeEstimate": 4848,
      "score": 327.6135274769355
    },
    {
      "id": 12499,
      "name": "Bowl of Mixed Berry Pie Filling",
      "icon": "https://render.guildwars2.com/file/FF69CEC01E0F087AEB40474E6095607856A42A4F/433678.png",
      "rarity": "Basic",
      "buy": 272,
      "sell": 605,
      "supply": 29165,
      "demand": 4602,
      "unitProfit": 242,
      "marginPct": 88.97058823529412,
      "dailyVolumeEstimate": 4602,
      "score": 325.9029102663021
    },
    {
      "id": 20740,
      "name": "Violet Ice Dye",
      "icon": "https://render.guildwars2.com/file/4C6A69A2F750523C239A075656E719ED07492B2E/66652.png",
      "rarity": "Fine",
      "buy": 7,
      "sell": 17,
      "supply": 4956,
      "demand": 1773,
      "unitProfit": 7,
      "marginPct": 100,
      "dailyVolumeEstimate": 1773,
      "score": 324.89536154957074
    },
    {
      "id": 71931,
      "name": "Karka Helm Skin",
      "icon": "https://render.guildwars2.com/file/B9F4A85C1DD60E497A914542689DF90777189741/1010525.png",
      "rarity": "Exotic",
      "buy": 2101,
      "sell": 4701,
      "supply": 3961,
      "demand": 7210,
      "unitProfit": 1895,
      "marginPct": 90.19514516896716,
      "dailyVolumeEstimate": 3961,
      "score": 324.5144180356398
    },
    {
      "id": 19775,
      "name": "Rampager's Elder Inscription",
      "icon": "https://render.guildwars2.com/file/AB49649A3F02991A4656150E062E9771D1073A01/340427.png",
      "rarity": "Fine",
      "buy": 93,
      "sell": 208,
      "supply": 9045,
      "demand": 3912,
      "unitProfit": 84,
      "marginPct": 90.32258064516128,
      "dailyVolumeEstimate": 3912,
      "score": 324.48476045554526
    },
    {
      "id": 75993,
      "name": "Recipe: Viper's Draconic Gauntlets",
      "icon": "https://render.guildwars2.com/file/2165062CDCFBAAA0173AB39DF7EB10A2120816D0/849293.png",
      "rarity": "Exotic",
      "buy": 10,
      "sell": 22,
      "supply": 8764,
      "demand": 3981,
      "unitProfit": 9,
      "marginPct": 90,
      "dailyVolumeEstimate": 3981,
      "score": 324.00911301222516
    },
    {
      "id": 12473,
      "name": "Loaf of Omnomberry Bread",
      "icon": "https://render.guildwars2.com/file/2EF807DDD55F4DD16F397A0199D2A027FD53BA90/433660.png",
      "rarity": "Fine",
      "buy": 351,
      "sell": 748,
      "supply": 9663,
      "demand": 17085,
      "unitProfit": 285,
      "marginPct": 81.19658119658119,
      "dailyVolumeEstimate": 9663,
      "score": 323.5811175395901
    },
    {
      "id": 24506,
      "name": "Topaz Lump",
      "icon": "https://render.guildwars2.com/file/20F826D4C42F7A9B9FCC122C0C80D8DA0AB9AE45/220945.png",
      "rarity": "Fine",
      "buy": 59,
      "sell": 119,
      "supply": 33943,
      "demand": 41247,
      "unitProfit": 42,
      "marginPct": 71.1864406779661,
      "dailyVolumeEstimate": 33943,
      "score": 322.5288928607788
    },
    {
      "id": 13146,
      "name": "Darksteel Pauldron Lining",
      "icon": "https://render.guildwars2.com/file/2F019DF07D7E317C5C5D06D5DD716770F8E6300D/219585.png",
      "rarity": "Basic",
      "buy": 9,
      "sell": 21,
      "supply": 3735,
      "demand": 1629,
      "unitProfit": 9,
      "marginPct": 100,
      "dailyVolumeEstimate": 1629,
      "score": 321.2187604403958
    },
    {
      "id": 21655,
      "name": "Torn Pelt",
      "icon": "https://render.guildwars2.com/file/63E475033A69F1966537C09E5610F971CBE6CD02/223811.png",
      "rarity": "Basic",
      "buy": 39,
      "sell": 89,
      "supply": 2421,
      "demand": 8855,
      "unitProfit": 37,
      "marginPct": 94.87179487179486,
      "dailyVolumeEstimate": 2421,
      "score": 321.0626747073339
    },
    {
      "id": 9300,
      "name": "Large Miner's Bag",
      "icon": "https://render.guildwars2.com/file/EBC5CEC199D1E51B02756A1C796A65E9D24F04B5/63171.png",
      "rarity": "Basic",
      "buy": 62,
      "sell": 131,
      "supply": 11334,
      "demand": 11591,
      "unitProfit": 49,
      "marginPct": 79.03225806451613,
      "dailyVolumeEstimate": 11334,
      "score": 320.43008822365204
    },
    {
      "id": 66612,
      "name": "Rampager's Adventurer's Scarf",
      "icon": "https://render.guildwars2.com/file/364CAB0FB673800ED57AF256291301E45AFDDE9D/831464.png",
      "rarity": "Exotic",
      "buy": 2418,
      "sell": 5550,
      "supply": 2297,
      "demand": 2813,
      "unitProfit": 2299,
      "marginPct": 95.07857733664186,
      "dailyVolumeEstimate": 2297,
      "score": 319.5923782458999
    },
    {
      "id": 12139,
      "name": "Bowl of Front Line Stew",
      "icon": "https://render.guildwars2.com/file/1F0595F2252BEFA1396235A0A56DFD499C95D455/63085.png",
      "rarity": "Basic",
      "buy": 128,
      "sell": 300,
      "supply": 1662,
      "demand": 5515,
      "unitProfit": 127,
      "marginPct": 99.21875,
      "dailyVolumeEstimate": 1662,
      "score": 319.5729028522492
    },
    {
      "id": 13121,
      "name": "Iron Scale Legging Panel",
      "icon": "https://render.guildwars2.com/file/9BA2163570E4504918E79507375AEE3E40C2DA06/340097.png",
      "rarity": "Basic",
      "buy": 392,
      "sell": 904,
      "supply": 4869,
      "demand": 2057,
      "unitProfit": 377,
      "marginPct": 96.1734693877551,
      "dailyVolumeEstimate": 2057,
      "score": 318.6655369007036
    },
    {
      "id": 19837,
      "name": "Berserker's Darksteel Plated Inscription",
      "icon": "https://render.guildwars2.com/file/0D7308FE0231210708F7C5E30604CA50B0A37F6A/66021.png",
      "rarity": "Masterwork",
      "buy": 1807,
      "sell": 4206,
      "supply": 2556,
      "demand": 1797,
      "unitProfit": 1768,
      "marginPct": 97.84172661870504,
      "dailyVolumeEstimate": 1797,
      "score": 318.45424279569824
    },
    {
      "id": 12998,
      "name": "Orichalcum Spear Head",
      "icon": "https://render.guildwars2.com/file/CDFD78B9F041170D6ABA47042ABDB448BC276C2D/340056.png",
      "rarity": "Basic",
      "buy": 737,
      "sell": 1644,
      "supply": 3512,
      "demand": 5555,
      "unitProfit": 661,
      "marginPct": 89.68792401628222,
      "dailyVolumeEstimate": 3512,
      "score": 318.00451248473934
    },
    {
      "id": 12456,
      "name": "Mango Pie",
      "icon": "https://render.guildwars2.com/file/CEF6081FC507AFF365977FB548017169A6BEF065/433646.png",
      "rarity": "Fine",
      "buy": 152,
      "sell": 308,
      "supply": 24542,
      "demand": 27117,
      "unitProfit": 110,
      "marginPct": 72.36842105263158,
      "dailyVolumeEstimate": 24542,
      "score": 317.6921323762533
    },
    {
      "id": 38296,
      "name": "Recipe: Giver's Mithril Imbued Inscription",
      "icon": "https://render.guildwars2.com/file/A857C2732CCDF31A1B7F4B6654030A1D3E94424F/849388.png",
      "rarity": "Rare",
      "buy": 42,
      "sell": 98,
      "supply": 10760,
      "demand": 1792,
      "unitProfit": 41,
      "marginPct": 97.61904761904762,
      "dailyVolumeEstimate": 1792,
      "score": 317.61140921916547
    },
    {
      "id": 13037,
      "name": "Wool Epaulet Padding",
      "icon": "https://render.guildwars2.com/file/1F4FEF6F41C299A7461763AC21D448464919D9B9/63525.png",
      "rarity": "Basic",
      "buy": 125,
      "sell": 294,
      "supply": 1485,
      "demand": 2986,
      "unitProfit": 125,
      "marginPct": 100,
      "dailyVolumeEstimate": 1485,
      "score": 317.2018809424556
    },
    {
      "id": 67386,
      "name": "Unopened Endless Bottle of Batwing Brew",
      "icon": "https://render.guildwars2.com/file/C4DBF3E24B3C9A1D2CABC55BF500F36C74F81E97/888368.png",
      "rarity": "Exotic",
      "buy": 716,
      "sell": 1511,
      "supply": 9956,
      "demand": 10829,
      "unitProfit": 568,
      "marginPct": 79.3296089385475,
      "dailyVolumeEstimate": 9956,
      "score": 317.1699709565441
    },
    {
      "id": 24613,
      "name": "Minor Sigil of Force",
      "icon": "https://render.guildwars2.com/file/5F089852CEDA66E947DC14B70661F806CAFD0D01/221010.png",
      "rarity": "Masterwork",
      "buy": 116,
      "sell": 246,
      "supply": 12736,
      "demand": 8988,
      "unitProfit": 93,
      "marginPct": 80.17241379310344,
      "dailyVolumeEstimate": 8988,
      "score": 316.9785848101402
    },
    {
      "id": 35729,
      "name": "Mystic Forge Node",
      "icon": "https://render.guildwars2.com/file/D74536FCCE724265DD0C44E4E8BD14E3EE1FD851/486250.png",
      "rarity": "Rare",
      "buy": 1009,
      "sell": 2209,
      "supply": 4920,
      "demand": 4712,
      "unitProfit": 869,
      "marginPct": 86.1248761149653,
      "dailyVolumeEstimate": 4712,
      "score": 316.36228693271784
    },
    {
      "id": 13101,
      "name": "Bronze Helmet Lining",
      "icon": "https://render.guildwars2.com/file/09AAF8D6EE71DD991114C5E34550AB3457DAE238/63560.png",
      "rarity": "Basic",
      "buy": 37,
      "sell": 80,
      "supply": 5852,
      "demand": 16268,
      "unitProfit": 31,
      "marginPct": 83.78378378378379,
      "dailyVolumeEstimate": 5852,
      "score": 315.645227696053
    },
    {
      "id": 20457,
      "name": "Country Teal Dye",
      "icon": "https://render.guildwars2.com/file/06DF4AD10F92FDC3AB0EA1D8411038D44758BD52/66654.png",
      "rarity": "Fine",
      "buy": 8,
      "sell": 18,
      "supply": 4040,
      "demand": 6832,
      "unitProfit": 7,
      "marginPct": 87.5,
      "dailyVolumeEstimate": 4040,
      "score": 315.5677744137317
    },
    {
      "id": 24327,
      "name": "Crystal Fragment",
      "icon": "https://render.guildwars2.com/file/43D43127072CF33D58B25E2FCC940435EB3D4548/66978.png",
      "rarity": "Rare",
      "buy": 160,
      "sell": 332,
      "supply": 13731,
      "demand": 47554,
      "unitProfit": 122,
      "marginPct": 76.25,
      "dailyVolumeEstimate": 13731,
      "score": 315.50220184997056
    },
    {
      "id": 107078,
      "name": "Visage of the Great Horse Fireworks",
      "icon": "https://render.guildwars2.com/file/3EDF686E07DAD8E550C62C1F7E77094567332269/3744699.png",
      "rarity": "Exotic",
      "buy": 47,
      "sell": 95,
      "supply": 62062,
      "demand": 30842,
      "unitProfit": 33,
      "marginPct": 70.2127659574468,
      "dailyVolumeEstimate": 30842,
      "score": 315.19610267592196
    },
    {
      "id": 12269,
      "name": "Bowl of Blueberry Pie Filling",
      "icon": "https://render.guildwars2.com/file/5BDCE0F805EB5BCE90CB44C7ED6897DB2CC745CD/63343.png",
      "rarity": "Basic",
      "buy": 52,
      "sell": 110,
      "supply": 34421,
      "demand": 9887,
      "unitProfit": 41,
      "marginPct": 78.84615384615384,
      "dailyVolumeEstimate": 9887,
      "score": 314.9989360914122
    },
    {
      "id": 12420,
      "name": "Mixed Berry Pie",
      "icon": "https://render.guildwars2.com/file/E3F852DB4B7D2D6CA198FCCCE4A7394D08EBF6F0/433614.png",
      "rarity": "Fine",
      "buy": 137,
      "sell": 278,
      "supply": 25399,
      "demand": 22850,
      "unitProfit": 99,
      "marginPct": 72.26277372262774,
      "dailyVolumeEstimate": 22850,
      "score": 314.9865808912348
    },
    {
      "id": 62950,
      "name": "Sturdy Weaponsmith's Tools",
      "icon": "https://render.guildwars2.com/file/0DEAEB1B3D9C46C60EE2E10C20EAA0767F047701/866737.png",
      "rarity": "Fine",
      "buy": 863,
      "sell": 1995,
      "supply": 5518,
      "demand": 1785,
      "unitProfit": 832,
      "marginPct": 96.40787949015063,
      "dailyVolumeEstimate": 1785,
      "score": 313.5069953867558
    },
    {
      "id": 12365,
      "name": "Cherry Tart",
      "icon": "https://render.guildwars2.com/file/77C0A2FE6206EBA76FF073365F0DD8A3FF5EEE4C/339914.png",
      "rarity": "Fine",
      "buy": 140,
      "sell": 300,
      "supply": 6553,
      "demand": 26426,
      "unitProfit": 115,
      "marginPct": 82.14285714285714,
      "dailyVolumeEstimate": 6553,
      "score": 313.49874304309355
    },
    {
      "id": 12839,
      "name": "Mithril Greatsword Blade",
      "icon": "https://render.guildwars2.com/file/0DD0EA9C9ABCF71BC5490C33BBCA1FBF04A37C48/219514.png",
      "rarity": "Basic",
      "buy": 153,
      "sell": 332,
      "supply": 16191,
      "demand": 5074,
      "unitProfit": 129,
      "marginPct": 84.31372549019608,
      "dailyVolumeEstimate": 5074,
      "score": 312.4191176532662
    },
    {
      "id": 19839,
      "name": "Carrion Hard Inscription",
      "icon": "https://render.guildwars2.com/file/4ED5C61EA6037C7735097B29F5D536AD03211A7F/66023.png",
      "rarity": "Fine",
      "buy": 659,
      "sell": 1498,
      "supply": 2240,
      "demand": 3309,
      "unitProfit": 614,
      "marginPct": 93.17147192716236,
      "dailyVolumeEstimate": 2240,
      "score": 312.1655993797462
    }
  ]
}